[
    {"text": "1", "description": "Left Punch", "game": "Tekken 7", "directional_inputs": [""], "attack_buttons": ["Left Punch"], "group": "attacks", "icon": ""},
    {"text": "2", "description": "Right Punch", "game": "Tekken 7", "directional_inputs": [""], "attack_buttons": ["Right Punch"], "group": "attacks", "icon": ""},
    {"text": "3", "description": "Left Kick", "game": "Tekken 7", "directional_inputs": [""], "attack_buttons": ["Left Kick"], "group": "attacks", "icon": ""},
    {"text": "4", "description": "Right Kick", "game": "Tekken 7", "directional_inputs": [""], "attack_buttons": ["Right Kick"], "group": "attacks", "icon": ""},
    {"text": "1 + 2", "description": "Left Punch + Right Punch", "game": "Tekken 7", "directional_inputs": [""], "attack_buttons": ["Left Punch + Right Punch"], "group": "attacks", "icon": ""},
    {"text": "1 + 3", "description": "Left Punch + Left Kick", "game": "Tekken 7", "directional_inputs": [""], "attack_buttons": ["Left Punch + Left Kick"], "group": "attacks", "icon": ""},
    {"text": "1 + 4", "description": "Left Punch + Right Kick", "game": "Tekken 7", "directional_inputs": [""], "attack_buttons": ["Left Punch + Right Kick"], "group": "attacks", "icon": ""},
    {"text": "2 + 3", "description": "Right Punch + Left Kick", "game": "Tekken 7", "directional_inputs": [""], "attack_buttons": ["Right Punch + Left Kick"], "group": "attacks", "icon": ""},
    {"text": "2 + 4", "description": "Right Punch + Right Kick", "game": "Tekken 7", "directional_inputs": [""], "attack_buttons": ["Right Punch + Right Kick"], "group": "attacks", "icon": ""},
    {"text": "3 + 4", "description": "Left Kick + Right Kick", "game": "Tekken 7", "directional_inputs": [""], "attack_buttons": ["Left Kick + Right Kick"], "group": "attacks", "icon": ""},
    {"text": "1 + 2 + 3", "description": "Left Punch + Right Punch + Left Kick", "game": "Tekken 7", "directional_inputs": [""], "attack_buttons": ["Left Punch + Right Punch + Left Kick"], "group": "attacks", "icon": ""},
    {"text": "1 + 2 + 4", "description": "Left Punch + Right Punch + Right Kick", "game": "Tekken 7", "directional_inputs": [""], "attack_buttons": ["Left Punch + Right Punch + Right Kick"], "group": "attacks", "icon": ""},
    {"text": "1 + 3 + 4", "description": "Left Punch + Left Kick + Right Kick", "game": "Tekken 7", "directional_inputs": [""], "attack_buttons": ["Left Punch + Left Kick + Right Kick"], "group": "attacks", "icon": ""},
    {"text": "2 + 3 + 4", "description": "Right Punch + Left Kick + Right Kick", "game": "Tekken 7", "directional_inputs": [""], "attack_buttons": ["Right Punch + Left Kick + Right Kick"], "group": "attacks", "icon": ""},
    {"text": "1 + 2 + 3 + 4", "description": "Left Punch + Right Punch + Left Kick + Right Kick", "game": "Tekken 7", "directional_inputs": [""], "attack_buttons": ["Left Punch + Right Punch + Left Kick + Right Kick"], "group": "attacks", "icon": ""},
    {"text": "u", "description": "Up", "game": "Tekken 7", "directional_inputs": ["Up"], "attack_buttons": [""], "group": "directions", "icon": ""},
    {"text": "d", "description": "Down", "game": "Tekken 7", "directional_inputs": ["Down"], "attack_buttons": [""], "group": "directions", "icon": ""},
    {"text": "f", "description": "Forward", "game": "Tekken 7", "directional_inputs": ["Forward"], "attack_buttons": [""], "group": "directions", "icon": ""},
    {"text": "b", "description": "Back", "game": "Tekken 7", "directional_inputs": ["Back"], "attack_buttons": [""], "group": "directions", "icon": ""},
    {"text": "uf", "description": "Up and Forward", "game": "Tekken 7", "directional_inputs": ["Up Forward"], "attack_buttons": [""], "group": "directions", "icon": ""},
    {"text": "df", "description": "Down and Forward", "game": "Tekken 7", "directional_inputs": ["Down Forward"], "attack_buttons": [""], "group": "directions", "icon": ""},
    {"text": "ub", "description": "Up and Back", "game": "Tekken 7", "directional_inputs": ["Up Back"], "attack_buttons": [""], "group": "directions", "icon": ""},
    {"text": "db", "description": "Down and Back", "game": "Tekken 7", "directional_inputs": ["Down Back"], "attack_buttons": [""], "group": "directions", "icon": ""},
    {"text": "n", "description": "Neutral", "game": "Tekken 7", "directional_inputs": ["Neutral"], "attack_buttons": [""], "group": "directions", "icon": ""},
    {"text": "U", "description": "Up (hold)", "game": "Tekken 7", "directional_inputs": ["Up (hold)"], "attack_buttons": [""], "group": "directions", "icon": ""},
    {"text": "D", "description": "Down (hold)", "game": "Tekken 7", "directional_inputs": ["Down (hold)"], "attack_buttons": [""], "group": "directions", "icon": ""},
    {"text": "F", "description": "Forward (hold)", "game": "Tekken 7", "directional_inputs": ["Forward (hold)"], "attack_buttons": [""], "group": "directions", "icon": ""},
    {"text": "B", "description": "Back (hold)", "game": "Tekken 7", "directional_inputs": ["Back (hold)"], "attack_buttons": [""], "group": "directions", "icon": ""},
    {"text": "U/F", "description": "Up and forward (hold)", "game": "Tekken 7", "directional_inputs": ["Up Forward (hold)"], "attack_buttons": [""], "group": "directions", "icon": ""},
    {"text": "D/F", "description": "Down and forward (hold)", "game": "Tekken 7", "directional_inputs": ["Down Forward (hold)"], "attack_buttons": [""], "group": "directions", "icon": ""},
    {"text": "U/B", "description": "Up and back (hold)", "game": "Tekken 7", "directional_inputs": ["Up Back (hold)"], "attack_buttons": [""], "group": "directions", "icon": ""},
    {"text": "D/B", "description": "Down and back (hold)", "game": "Tekken 7", "directional_inputs": ["Down Back (hold)"], "attack_buttons": [""], "group": "directions", "icon": ""},
    {"text": "+", "description": "Press Simultaneously", "game": "Tekken 7", "directional_inputs": [""], "attack_buttons": [""], "group": "other", "icon": ""},
    {"text": ",", "description": "Followed By (one right after the other)", "game": "Tekken 7", "directional_inputs": [""], "attack_buttons": [""], "group": "other", "icon": ""},
    {"text": ">", "description": "Next move", "game": "Tekken 7", "directional_inputs": [""], "attack_buttons": [""], "group": "other", "icon": "followed-by.svg"},
    {"text": "~", "description": "Slide (one immediately after the other)", "game": "Tekken 7", "directional_inputs": [""], "attack_buttons": [""], "group": "other", "icon": ""},
    {"text": "_", "description": "Or (move operands are interchangeable)", "game": "Tekken 7", "directional_inputs": [""], "attack_buttons": [""], "group": "other", "icon": ""},
    {"text": ":", "description": "Requires Just Frame Input (precise execution time)", "game": "Tekken 7", "directional_inputs": [""], "attack_buttons": [""], "group": "other", "icon": ""},
    {"text": "FC", "description": "Full Crouch (do while in a crouched position)", "game": "Tekken 7", "directional_inputs": [""], "attack_buttons": [""], "group": "other", "icon": ""},
    {"text": "WS", "description": "While Standing (while standing up)", "game": "Tekken 7", "directional_inputs": [""], "attack_buttons": [""], "group": "other", "icon": ""},
    {"text": "WR", "description": "While Running", "game": "Tekken 7", "directional_inputs": [""], "attack_buttons": [""], "group": "other", "icon": ""},
    {"text": "BT", "description": "Back turned towards opponent", "game": "Tekken 7", "directional_inputs": [""], "attack_buttons": [""], "group": "other", "icon": ""},
    {"text": "SS", "description": "Sidestep", "game": "Tekken 7", "directional_inputs": [""], "attack_buttons": [""], "group": "other", "icon": ""},
    {"text": "SSL", "description": "Sidestep Left", "game": "Tekken 7", "directional_inputs": ["Up"], "attack_buttons": [""], "group": "other", "icon": ""},
    {"text": "SSR", "description": "Sidestep Right", "game": "Tekken 7", "directional_inputs": ["Down"], "attack_buttons": [""], "group": "other", "icon": ""},
    {"text": "CH", "description": "Counter Hit (land hit during opponent attack startup animation)", "game": "Tekken 7", "directional_inputs": [""], "attack_buttons": [""], "group": "other", "icon": ""},
    {"text": "[", "description": "Optional input (start)", "game": "Tekken 7", "directional_inputs": [""], "attack_buttons": [""], "group": "other", "icon": ""},
    {"text": "]", "description": "Optional input (end)", "game": "Tekken 7", "directional_inputs": [""], "attack_buttons": [""], "group": "other", "icon": ""},
    {"text": "{", "description": "Buttons needed to break throw (start)", "game": "Tekken 7", "directional_inputs": [""], "attack_buttons": [""], "group": "other", "icon": ""},
    {"text": "}", "description": "Buttons needed to break throw (end)", "game": "Tekken 7", "directional_inputs": [""], "attack_buttons": [""], "group": "other", "icon": ""},
    {"text": "*", "description": "Press and hold", "game": "Tekken 7", "directional_inputs": [""], "attack_buttons": [""], "group": "other", "icon": ""},
    {"text": "!", "description": "Unblockable hit", "game": "Tekken 7", "directional_inputs": [""], "attack_buttons": [""], "group": "other", "icon": ""},
    {"text": "(!)", "description": "Unblockable hit that can be ducked", "game": "Tekken 7", "directional_inputs": [""], "attack_buttons": [""], "group": "other", "icon": ""},
    {"text": "[!]", "description": "Unblockable hit that hits grounded opponents", "game": "Tekken 7", "directional_inputs": [""], "attack_buttons": [""], "group": "other", "icon": ""},
    {"text": "FD/FT", "description": "Face Down / Feet Toward Opponent", "game": "Tekken 7", "directional_inputs": [""], "attack_buttons": [""], "group": "other", "icon": ""},
    {"text": "FD/FA", "description": "Face Down / Feet Away from Opponent", "game": "Tekken 7", "directional_inputs": [""], "attack_buttons": [""], "group": "other", "icon": ""},
    {"text": "FU/FT", "description": "Face Up / Feet Toward Opponent", "game": "Tekken 7", "directional_inputs": [""], "attack_buttons": [""], "group": "other", "icon": ""},
    {"text": "FU/FA", "description": "Grounded opponent ('on the ground')", "game": "Tekken 7", "directional_inputs": [""], "attack_buttons": [""], "group": "other", "icon": ""},
    {"text": "OTG", "description": "Face Up / Feet Away from Opponent", "game": "Tekken 7", "directional_inputs": [""], "attack_buttons": [""], "group": "other", "icon": ""},
    {"text": "cc", "description": "Crouch Cancel", "game": "Tekken 7", "directional_inputs": ["Up", "Neutral"], "attack_buttons": [""], "group": "other", "icon": ""},
    {"text": "S!", "description": "Screw (Corkscrew, Tailspin)", "game": "Tekken 7", "directional_inputs": [""], "attack_buttons": [""], "group": "other", "icon": ""},
    {"text": "W!", "description": "Wall Splat / Wall Bounce", "game": "Tekken 7", "directional_inputs": [""], "attack_buttons": [""], "group": "other", "icon": ""},
    {"text": "WB!", "description": "Wall Break", "game": "Tekken 7", "directional_inputs": [""], "attack_buttons": [""], "group": "other", "icon": ""},
    {"text": "F!", "description": "Floor Break", "game": "Tekken 7", "directional_inputs": [""], "attack_buttons": [""], "group": "other", "icon": ""},
    {"text": "FB!", "description": "Floor Break", "game": "Tekken 7", "directional_inputs": [""], "attack_buttons": [""], "group": "other", "icon": ""},
    {"text": "BB!", "description": "Balcony Break", "game": "Tekken 7", "directional_inputs": [""], "attack_buttons": [""], "group": "other", "icon": ""},
    {"text": "RD", "description": "Rage Drive", "game": "Tekken 7", "directional_inputs": [""], "attack_buttons": [""], "group": "other", "icon": ""},
    {"text": "RA", "description": "Rage Art", "game": "Tekken 7", "directional_inputs": [""], "attack_buttons": [""], "group": "other", "icon": ""},
    {"text": "R", "description": "Rage (in Rage Mode)", "game": "Tekken 7", "directional_inputs": [""], "attack_buttons": [""], "group": "other", "icon": ""}
]
