[
    {"text": "1", "description": "Left Punch", "game": "Tekken 8", "directional_inputs": [""], "attack_buttons": ["Left Punch"], "group": "attacks", "icon": ""},
    {"text": "2", "description": "Right Punch", "game": "Tekken 8", "directional_inputs": [""], "attack_buttons": ["Right Punch"], "group": "attacks", "icon": ""},
    {"text": "3", "description": "Left Kick", "game": "Tekken 8", "directional_inputs": [""], "attack_buttons": ["Left Kick"], "group": "attacks", "icon": ""},
    {"text": "4", "description": "Right Kick", "game": "Tekken 8", "directional_inputs": [""], "attack_buttons": ["Right Kick"], "group": "attacks", "icon": ""},
    {"text": "1 + 2", "description": "Left Punch + Right Punch", "game": "Tekken 8", "directional_inputs": [""], "attack_buttons": ["Left Punch + Right Punch"], "group": "attacks", "icon": ""},
    {"text": "1 + 3", "description": "Left Punch + Left Kick", "game": "Tekken 8", "directional_inputs": [""], "attack_buttons": ["Left Punch + Left Kick"], "group": "attacks", "icon": ""},
    {"text": "1 + 4", "description": "Left Punch + Right Kick", "game": "Tekken 8", "directional_inputs": [""], "attack_buttons": ["Left Punch + Right Kick"], "group": "attacks", "icon": ""},
    {"text": "2 + 3", "description": "Right Punch + Left Kick", "game": "Tekken 8", "directional_inputs": [""], "attack_buttons": ["Right Punch + Left Kick"], "group": "attacks", "icon": ""},
    {"text": "2 + 4", "description": "Right Punch + Right Kick", "game": "Tekken 8", "directional_inputs": [""], "attack_buttons": ["Right Punch + Right Kick"], "group": "attacks", "icon": ""},
    {"text": "3 + 4", "description": "Left Kick + Right Kick", "game": "Tekken 8", "directional_inputs": [""], "attack_buttons": ["Left Kick + Right Kick"], "group": "attacks", "icon": ""},
    {"text": "1 + 2 + 3", "description": "Left Punch + Right Punch + Left Kick", "game": "Tekken 8", "directional_inputs": [""], "attack_buttons": ["Left Punch + Right Punch + Left Kick"], "group": "attacks", "icon": ""},
    {"text": "1 + 2 + 4", "description": "Left Punch + Right Punch + Right Kick", "game": "Tekken 8", "directional_inputs": [""], "attack_buttons": ["Left Punch + Right Punch + Right Kick"], "group": "attacks", "icon": ""},
    {"text": "1 + 3 + 4", "description": "Left Punch + Left Kick + Right Kick", "game": "Tekken 8", "directional_inputs": [""], "attack_buttons": ["Left Punch + Left Kick + Right Kick"], "group": "attacks", "icon": ""},
    {"text": "2 + 3 + 4", "description": "Right Punch + Left Kick + Right Kick", "game": "Tekken 8", "directional_inputs": [""], "attack_buttons": ["Right Punch + Left Kick + Right Kick"], "group": "attacks", "icon": ""},
    {"text": "1 + 2 + 3 + 4", "description": "Left Punch + Right Punch + Left Kick + Right Kick", "game": "Tekken 8", "directional_inputs": [""], "attack_buttons": ["Left Punch + Right Punch + Left Kick + Right Kick"], "group": "attacks", "icon": ""},
    {"text": "u", "description": "Up", "game": "Tekken 8", "directional_inputs": ["Up"], "attack_buttons": [""], "group": "directions", "icon": ""},
    {"text": "d", "description": "Down", "game": "Tekken 8", "directional_inputs": ["Down"], "attack_buttons": [""], "group": "directions", "icon": ""},
    {"text": "f", "description": "Forward", "game": "Tekken 8", "directional_inputs": ["Forward"], "attack_buttons": [""], "group": "directions", "icon": ""},
    {"text": "b", "description": "Back", "game": "Tekken 8", "directional_inputs": ["Back"], "attack_buttons": [""], "group": "directions", "icon": ""},
    {"text": "uf", "description": "Up Forward", "game": "Tekken 8", "directional_inputs": ["Up Forward"], "attack_buttons": [""], "group": "directions", "icon": ""},
    {"text": "df", "description": "Down Forward", "game": "Tekken 8", "directional_inputs": ["Down Forward"], "attack_buttons": [""], "group": "directions", "icon": ""},
    {"text": "ub", "description": "Up Back", "game": "Tekken 8", "directional_inputs": ["Up Back"], "attack_buttons": [""], "group": "directions", "icon": ""},
    {"text": "db", "description": "Down Back", "game": "Tekken 8", "directional_inputs": ["Down Back"], "attack_buttons": [""], "group": "directions", "icon": ""},
    {"text": "n", "description": "Neutral", "game": "Tekken 8", "directional_inputs": ["Neutral"], "attack_buttons": [""], "group": "directions", "icon": ""},
    {"text": "U", "description": "Up (hold)", "game": "Tekken 8", "directional_inputs": ["Up (hold)"], "attack_buttons": [""], "group": "directions", "icon": ""},
    {"text": "D", "description": "Down (hold)", "game": "Tekken 8", "directional_inputs": ["Down (hold)"], "attack_buttons": [""], "group": "directions", "icon": ""},
    {"text": "F", "description": "Forward (hold)", "game": "Tekken 8", "directional_inputs": ["Forward (hold)"], "attack_buttons": [""], "group": "directions", "icon": ""},
    {"text": "B", "description": "Back (hold)", "game": "Tekken 8", "directional_inputs": ["Back (hold)"], "attack_buttons": [""], "group": "directions", "icon": ""},
    {"text": "U/F", "description": "Up Forward (hold)", "game": "Tekken 8", "directional_inputs": ["Up Forward (hold)"], "attack_buttons": [""], "group": "directions", "icon": ""},
    {"text": "D/F", "description": "Down Forward (hold)", "game": "Tekken 8", "directional_inputs": ["Down Forward (hold)"], "attack_buttons": [""], "group": "directions", "icon": ""},
    {"text": "U/B", "description": "Up Back (hold)", "game": "Tekken 8", "directional_inputs": ["Up Back (hold)"], "attack_buttons": [""], "group": "directions", "icon": ""},
    {"text": "D/B", "description": "Down Back (hold)", "game": "Tekken 8", "directional_inputs": ["Down Back (hold)"], "attack_buttons": [""], "group": "directions", "icon": ""},
    {"text": "+", "description": "Press Simultaneously", "game": "Tekken 8", "directional_inputs": [""], "attack_buttons": [""], "group": "other", "icon": ""},
    {"text": ",", "description": "Followed By (one right after the other)", "game": "Tekken 8", "directional_inputs": [""], "attack_buttons": [""], "group": "other", "icon": ""},
    {"text": ">", "description": "Next move", "game": "Tekken 8", "directional_inputs": [""], "attack_buttons": [""], "group": "other", "icon": "followed-by.svg"},
    {"text": "<", "description": "Delayed input", "game": "Tekken 8", "directional_inputs": [""], "attack_buttons": [""], "group": "other", "icon": "followed-by.svg"},
    {"text": "~", "description": "Slide (one immediately after the other)", "game": "Tekken 8", "directional_inputs": [""], "attack_buttons": [""], "group": "other", "icon": ""},
    {"text": "_", "description": "Or (move operands are interchangeable)", "game": "Tekken 8", "directional_inputs": [""], "attack_buttons": [""], "group": "other", "icon": ""},
    {"text": ":", "description": "Requires Just Frame Input (precise execution time)", "game": "Tekken 8", "directional_inputs": [""], "attack_buttons": [""], "group": "other", "icon": ""},
    {"text": "FC", "description": "Full Crouch (do while in a crouched position)", "game": "Tekken 8", "directional_inputs": [""], "attack_buttons": [""], "group": "other", "icon": ""},
    {"text": "WS", "description": "While Standing (while standing up)", "game": "Tekken 8", "directional_inputs": [""], "attack_buttons": [""], "group": "other", "icon": ""},
    {"text": "WR", "description": "While Running", "game": "Tekken 8", "directional_inputs": [""], "attack_buttons": [""], "group": "other", "icon": ""},
    {"text": "BT", "description": "Back turned towards opponent", "game": "Tekken 8", "directional_inputs": [""], "attack_buttons": [""], "group": "other", "icon": ""},
    {"text": "SS", "description": "Sidestep", "game": "Tekken 8", "directional_inputs": [""], "attack_buttons": [""], "group": "other", "icon": ""},
    {"text": "SSL", "description": "Sidestep Left", "game": "Tekken 8", "directional_inputs": ["Up"], "attack_buttons": [""], "group": "other", "icon": ""},
    {"text": "SSR", "description": "Sidestep Right", "game": "Tekken 8", "directional_inputs": ["Down"], "attack_buttons": [""], "group": "other", "icon": ""},
    {"text": "CH", "description": "Counter Hit (land hit during opponent attack startup animation)", "game": "Tekken 8", "directional_inputs": [""], "attack_buttons": [""], "group": "other", "icon": ""},
    {"text": "[", "description": "Optional input (start)", "game": "Tekken 8", "directional_inputs": [""], "attack_buttons": [""], "group": "other", "icon": ""},
    {"text": "]", "description": "Optional input (end)", "game": "Tekken 8", "directional_inputs": [""], "attack_buttons": [""], "group": "other", "icon": ""},
    {"text": "{", "description": "Buttons needed to break throw (start)", "game": "Tekken 8", "directional_inputs": [""], "attack_buttons": [""], "group": "other", "icon": ""},
    {"text": "}", "description": "Buttons needed to break throw (end)", "game": "Tekken 8", "directional_inputs": [""], "attack_buttons": [""], "group": "other", "icon": ""},
    {"text": "*", "description": "Press and hold", "game": "Tekken 8", "directional_inputs": [""], "attack_buttons": [""], "group": "other", "icon": ""},
    {"text": "!", "description": "Unblockable hit", "game": "Tekken 8", "directional_inputs": [""], "attack_buttons": [""], "group": "other", "icon": ""},
    {"text": "(!)", "description": "Unblockable hit that can be ducked", "game": "Tekken 8", "directional_inputs": [""], "attack_buttons": [""], "group": "other", "icon": ""},
    {"text": "[!]", "description": "Unblockable hit that hits grounded opponents", "game": "Tekken 8", "directional_inputs": [""], "attack_buttons": [""], "group": "other", "icon": ""},
    {"text": "FD/FT", "description": "Face Down / Feet Toward Opponent", "game": "Tekken 8", "directional_inputs": [""], "attack_buttons": [""], "group": "other", "icon": ""},
    {"text": "FD/FA", "description": "Face Down / Feet Away from Opponent", "game": "Tekken 8", "directional_inputs": [""], "attack_buttons": [""], "group": "other", "icon": ""},
    {"text": "FU/FT", "description": "Face Up / Feet Toward Opponent", "game": "Tekken 8", "directional_inputs": [""], "attack_buttons": [""], "group": "other", "icon": ""},
    {"text": "FU/FA", "description": "Face Up / Feet Away from Opponent", "game": "Tekken 8", "directional_inputs": [""], "attack_buttons": [""], "group": "other", "icon": ""},
    {"text": "OTG", "description": "Grounded opponent ('on the ground')", "game": "Tekken 8", "directional_inputs": [""], "attack_buttons": [""], "group": "other", "icon": ""},
    {"text": "cc", "description": "Crouch Cancel", "game": "Tekken 8", "directional_inputs": ["Up", "Neutral"], "attack_buttons": [""], "group": "other", "icon": ""},
    {"text": "S!", "description": "Screw (Corkscrew, Tailspin)", "game": "Tekken 8", "directional_inputs": [""], "attack_buttons": [""], "group": "other", "icon": ""},
    {"text": "W!", "description": "Wall Splat / Wall Bounce", "game": "Tekken 8", "directional_inputs": [""], "attack_buttons": [""], "group": "other", "icon": ""},
    {"text": "WB!", "description": "Wall Break", "game": "Tekken 8", "directional_inputs": [""], "attack_buttons": [""], "group": "other", "icon": ""},
    {"text": "F!", "description": "Floor Break", "game": "Tekken 8", "directional_inputs": [""], "attack_buttons": [""], "group": "other", "icon": ""},
    {"text": "FB!", "description": "Floor Break", "game": "Tekken 8", "directional_inputs": [""], "attack_buttons": [""], "group": "other", "icon": ""},
    {"text": "BB!", "description": "Balcony Break", "game": "Tekken 8", "directional_inputs": [""], "attack_buttons": [""], "group": "other", "icon": ""},
    {"text": "RA", "description": "Rage Art", "game": "Tekken 8", "directional_inputs": [""], "attack_buttons": [""], "group": "other", "icon": ""},
    {"text": "R", "description": "Rage (in Rage Mode)", "game": "Tekken 8", "directional_inputs": [""], "attack_buttons": [""], "group": "other", "icon": ""},
    {"text": "etc.", "description": "Signifies that this move has follow ups", "game": "Tekken 8", "directional_inputs": [""], "attack_buttons": [""], "group": "other", "icon": ""},
    {"text": "P", "description": "Successful parry", "game": "Tekken 8", "directional_inputs": [""], "attack_buttons": [""], "group": "other", "icon": ""},
    {"text": "J", "description": "Jumping", "game": "Tekken 8", "directional_inputs": [""], "attack_buttons": [""], "group": "other", "icon": ""},
    {"text": "pc", "description": "Power Crush", "game": "Tekken 8", "directional_inputs": [""], "attack_buttons": [""], "group": "other", "icon": ""},
    {"text": "or", "description": "or", "game": "Tekken 8", "directional_inputs": [""], "attack_buttons": [""], "group": "other", "icon": ""},
    {"text": "xx", "description": "Cancel into the next move", "game": "Tekken 8", "directional_inputs": [""], "attack_buttons": [""], "group": "other", "icon": ""},
    {"text": "CD", "description": "Crouch Dash", "game": "Tekken 8", "directional_inputs": [""], "attack_buttons": [""], "group": "other", "icon": ""},
    {"text": "On hit", "description": "On hit", "game": "Tekken 8", "directional_inputs": [""], "attack_buttons": [""], "group": "other", "icon": ""},
    {"text": "On block", "description": "On block", "game": "Tekken 8", "directional_inputs": [""], "attack_buttons": [""], "group": "other", "icon": ""},
    {"text": "SS", "description": "During Side Step", "game": "Tekken 8", "directional_inputs": [""], "attack_buttons": [""], "group": "other", "icon": ""},
    {"text": "Fr.LS", "description": "Approach opponent from left side", "game": "Tekken 8", "directional_inputs": [""], "attack_buttons": [""], "group": "other", "icon": ""},
    {"text": "Fr.RS", "description": "Approach opponent from right side", "game": "Tekken 8", "directional_inputs": [""], "attack_buttons": [""], "group": "other", "icon": ""},
    {"text": "Fr.B", "description": "Approach opponent from behind", "game": "Tekken 8", "directional_inputs": [""], "attack_buttons": [""], "group": "other", "icon": ""},
    {"text": "Fr.F", "description": "Approach opponent from front", "game": "Tekken 8", "directional_inputs": [""], "attack_buttons": [""], "group": "other", "icon": ""},
    {"text": "Op.A", "description": "Approach airborne opponent", "game": "Tekken 8", "directional_inputs": [""], "attack_buttons": [""], "group": "other", "icon": ""},
    {"text": "Op.C", "description": "Approach crouching opponent", "game": "Tekken 8", "directional_inputs": [""], "attack_buttons": [""], "group": "other", "icon": ""},
    {"text": "Op.FU", "description": "Approach face up opponent", "game": "Tekken 8", "directional_inputs": [""], "attack_buttons": [""], "group": "other", "icon": ""},
    {"text": "Op.FD", "description": "Approach face down opponent", "game": "Tekken 8", "directional_inputs": [""], "attack_buttons": [""], "group": "other", "icon": ""},
    {"text": "B.Op.F", "description": "By opponent's feet", "game": "Tekken 8", "directional_inputs": [""], "attack_buttons": [""], "group": "other", "icon": ""},
    {"text": "B.Op.H", "description": "By opponent's head", "game": "Tekken 8", "directional_inputs": [""], "attack_buttons": [""], "group": "other", "icon": ""},
    {"text": "B.Op.S", "description": "By opponent's side", "game": "Tekken 8", "directional_inputs": [""], "attack_buttons": [""], "group": "other", "icon": ""},
    {"text": "Tw.A", "description": "Time with opponent attack", "game": "Tekken 8", "directional_inputs": [""], "attack_buttons": [""], "group": "other", "icon": ""},
    {"text": "Tw.LA", "description": "Time with opponent low attack", "game": "Tekken 8", "directional_inputs": [""], "attack_buttons": [""], "group": "other", "icon": ""},
    {"text": "Tw.MA", "description": "Time with opponent mid attack", "game": "Tekken 8", "directional_inputs": [""], "attack_buttons": [""], "group": "other", "icon": ""},
    {"text": "Tw.HA", "description": "Time with opponent high attack", "game": "Tekken 8", "directional_inputs": [""], "attack_buttons": [""], "group": "other", "icon": ""},
    {"text": "Tw.T", "description": "Time with opponent throw", "game": "Tekken 8", "directional_inputs": [""], "attack_buttons": [""], "group": "other", "icon": ""},
    {"text": "Tw.P", "description": "Time with opponent punch", "game": "Tekken 8", "directional_inputs": [""], "attack_buttons": [""], "group": "other", "icon": ""},
    {"text": "Tw.RP", "description": "Time with opponent right punch", "game": "Tekken 8", "directional_inputs": [""], "attack_buttons": [""], "group": "other", "icon": ""},
    {"text": "Tw.K", "description": "Time with opponent kick", "game": "Tekken 8", "directional_inputs": [""], "attack_buttons": [""], "group": "other", "icon": ""},
    {"text": "Tw.LK", "description": "Time with opponent left kick", "game": "Tekken 8", "directional_inputs": [""], "attack_buttons": [""], "group": "other", "icon": ""},
    {"text": "Tw.RK", "description": "Time with opponent right kick", "game": "Tekken 8", "directional_inputs": [""], "attack_buttons": [""], "group": "other", "icon": ""},
    {"text": "Tk.LA", "description": "Take low attack from opponent", "game": "Tekken 8", "directional_inputs": [""], "attack_buttons": [""], "group": "other", "icon": ""},
    {"text": "Tk.MA", "description": "Take mid attack from opponent", "game": "Tekken 8", "directional_inputs": [""], "attack_buttons": [""], "group": "other", "icon": ""},
    {"text": "Tk.HA", "description": "Take high attack from opponent", "game": "Tekken 8", "directional_inputs": [""], "attack_buttons": [""], "group": "other", "icon": ""},
    {"text": "FrH.OTG", "description": "During front hit on ground", "game": "Tekken 8", "directional_inputs": [""], "attack_buttons": [""], "group": "other", "icon": ""},
    {"text": "During", "description": "During", "game": "Tekken 8", "directional_inputs": [""], "attack_buttons": [""], "group": "other", "icon": ""},
    {"text": "Heat", "description": "While in Heat", "game": "Tekken 8", "directional_inputs": [""], "attack_buttons": [""], "group": "other", "icon": ""},
    {"text": "and", "description": "and", "game": "Tekken 8", "directional_inputs": [""], "attack_buttons": [""], "group": "other", "icon": ""},
    {"text": "Hit.F", "description": "Hit from front", "game": "Tekken 8", "directional_inputs": [""], "attack_buttons": [""], "group": "other", "icon": ""},
    {"text": "max", "description": "perform preceding action to fullest extent", "game": "Tekken 8", "directional_inputs": [""], "attack_buttons": [""], "group": "other", "icon": ""},
    {"text": "takedown", "description": "Takedown an opponent (usually a tackle action)", "game": "Tekken 8", "directional_inputs": [""], "attack_buttons": [""], "group": "other", "icon": ""},
    {"text": "1x/match", "description": "Only once per match", "game": "Tekken 8", "directional_inputs": [""], "attack_buttons": [""], "group": "other", "icon": ""},
    {"text": "succeeds", "description": "After/if move succeeds", "game": "Tekken 8", "directional_inputs": [""], "attack_buttons": [""], "group": "other", "icon": ""},
    {"text": "fails", "description": "After/if move fails", "game": "Tekken 8", "directional_inputs": [""], "attack_buttons": [""], "group": "other", "icon": ""},
    {"text": "after", "description": "After", "game": "Tekken 8", "directional_inputs": [""], "attack_buttons": [""], "group": "other", "icon": ""},
    {"text": "before", "description": "Before", "game": "Tekken 8", "directional_inputs": [""], "attack_buttons": [""], "group": "other", "icon": ""},
    {"text": "hit", "description": "Move must connect", "game": "Tekken 8", "directional_inputs": [""], "attack_buttons": [""], "group": "other", "icon": ""},
    {"text": "block", "description": "Move must blocked", "game": "Tekken 8", "directional_inputs": [""], "attack_buttons": [""], "group": "other", "icon": ""},
    {"text": "whiff", "description": "Move must miss/whiff", "game": "Tekken 8", "directional_inputs": [""], "attack_buttons": [""], "group": "other", "icon": ""},
    {"text": "First", "description": "First hit", "game": "Tekken 8", "directional_inputs": [""], "attack_buttons": [""], "group": "other", "icon": ""},
    {"text": "Second", "description": "Second hit", "game": "Tekken 8", "directional_inputs": [""], "attack_buttons": [""], "group": "other", "icon": ""},
    {"text": "Third", "description": "Third hit", "game": "Tekken 8", "directional_inputs": [""], "attack_buttons": [""], "group": "other", "icon": ""},
    {"text": "Fourth", "description": "Fourth hit", "game": "Tekken 8", "directional_inputs": [""], "attack_buttons": [""], "group": "other", "icon": ""},
    {"text": "Fifth", "description": "Fifth hit", "game": "Tekken 8", "directional_inputs": [""], "attack_buttons": [""], "group": "other", "icon": ""},
    {"text": "front", "description": "Front", "game": "Tekken 8", "directional_inputs": [""], "attack_buttons": [""], "group": "other", "icon": ""},
    {"text": "back", "description": "Back", "game": "Tekken 8", "directional_inputs": [""], "attack_buttons": [""], "group": "other", "icon": ""},
    {"text": "...", "description": "Move continues on", "game": "Tekken 8", "directional_inputs": [""], "attack_buttons": [""], "group": "other", "icon": ""},
    {"text": "air", "description": "While in air", "game": "Tekken 8", "directional_inputs": [""], "attack_buttons": [""], "group": "other", "icon": ""},
    {"text": "landing", "description": "while landing", "game": "Tekken 8", "directional_inputs": [""], "attack_buttons": [""], "group": "other", "icon": ""},
    {"text": "parry", "description": "Parry opponent", "game": "Tekken 8", "directional_inputs": [""], "attack_buttons": [""], "group": "other", "icon": ""},
    {"text": "then", "description": "then", "game": "Tekken 8", "directional_inputs": [""], "attack_buttons": [""], "group": "other", "icon": ""},
    {"text": "of", "description": "of", "game": "Tekken 8", "directional_inputs": [""], "attack_buttons": [""], "group": "other", "icon": ""},
    {"text": "to", "description": "to", "game": "Tekken 8", "directional_inputs": [""], "attack_buttons": [""], "group": "other", "icon": ""},
    {"text": "with", "description": "with", "game": "Tekken 8", "directional_inputs": [""], "attack_buttons": [""], "group": "other", "icon": ""},
    {"text": "cl.", "description": "close range", "game": "Tekken 8", "directional_inputs": [""], "attack_buttons": [""], "group": "other", "icon": ""},
    {"text": "f.", "description": "far range", "game": "Tekken 8", "directional_inputs": [""], "attack_buttons": [""], "group": "other", "icon": ""}

    


]
